airsim_emulator/__init__.py
airsim_emulator/kinput.py
airsim_emulator/run_emulator.py
airsim_emulator/sBGC_adapter.py
airsim_emulator/serialtest.py
airsim_emulator/setup_path.py
airsim_emulator/test.py
airsim_emulator/visca_adapter.py
airsim_emulator-1.0.1.dist-info/LICENSE
airsim_emulator-1.0.1.dist-info/METADATA
airsim_emulator-1.0.1.dist-info/WHEEL
airsim_emulator-1.0.1.dist-info/top_level.txt
airsim_emulator-1.0.1.dist-info/RECORD
